{"name":"Actualizar mis datos personales","id":"hu-01-configuracion-de-cuenta;actualizar-mis-datos-personales","testSteps":[{"number":1,"description":"Example: {nombre\u003dJuan, apellidos\u003dGuillermos hoyos}","duration":11279,"startTime":"2021-12-17T10:48:01.766-05:00[America/Bogota]","screenshots":[{"screenshot":"54f86560acbcd8e4522e8500a9fb2906c10317f7c5cf3789453a7c2d43f1a752.png","timeStamp":1639756093045}],"result":"SUCCESS","precondition":false,"level":0,"children":[{"number":2,"description":"Given dado que me logueo en la pagina de linio","duration":2579,"startTime":"2021-12-17T10:48:01.772-05:00[America/Bogota]","screenshots":[{"screenshot":"fe05e3082bfe786550c777aa143a97568719f039c75d3e7e3445265a3378233a.png","timeStamp":1639756084351}],"result":"SUCCESS","precondition":false,"level":1},{"number":3,"description":"When vaya al apartado de configuracion de mi cuenta","duration":5527,"startTime":"2021-12-17T10:48:04.354-05:00[America/Bogota]","screenshots":[{"screenshot":"fe05e3082bfe786550c777aa143a97568719f039c75d3e7e3445265a3378233a.png","timeStamp":1639756084363},{"screenshot":"c457fd4917b88898bd8c3ae5bfd1d37a3420bdd784e3c5773b263f454d77a07d.png","timeStamp":1639756089881}],"result":"SUCCESS","precondition":false,"level":1,"children":[{"number":4,"description":"Sebastian hacer login","duration":5351,"startTime":"2021-12-17T10:48:04.520-05:00[America/Bogota]","screenshots":[{"screenshot":"ccdd7698ec2259ed3d1c40189d23e7441a84cc900c968453b87b2883a248b2ab.png","timeStamp":1639756084733},{"screenshot":"c457fd4917b88898bd8c3ae5bfd1d37a3420bdd784e3c5773b263f454d77a07d.png","timeStamp":1639756089871}],"result":"SUCCESS","precondition":false,"level":2,"children":[{"number":5,"description":"Sebastian enters \u0027sebastiansqa@yopmail.com\u0027 into ","duration":758,"startTime":"2021-12-17T10:48:04.774-05:00[America/Bogota]","screenshots":[{"screenshot":"92a07ba8a61ca46ebfe5d6ff5288693aa7ae5663ab977a8d24ffb12d52d9ac8d.png","timeStamp":1639756084969},{"screenshot":"732ce9f907d7392a202161ee8e2b1ea824da9ff508657b3d5ec33b88ea7a4961.png","timeStamp":1639756085532}],"result":"SUCCESS","precondition":false,"level":3},{"number":6,"description":"Sebastian enters \u0027AutomatizacionSQA2021\u0027 into ","duration":520,"startTime":"2021-12-17T10:48:05.536-05:00[America/Bogota]","screenshots":[{"screenshot":"732ce9f907d7392a202161ee8e2b1ea824da9ff508657b3d5ec33b88ea7a4961.png","timeStamp":1639756085546},{"screenshot":"3bb9e711e2e9e9f861773cbce5f2c302f5684d3282dcec3b7d4766475a3a5248.png","timeStamp":1639756086056}],"result":"SUCCESS","precondition":false,"level":3},{"number":7,"description":"Sebastian clicks on ","duration":1518,"startTime":"2021-12-17T10:48:06.057-05:00[America/Bogota]","screenshots":[{"screenshot":"3bb9e711e2e9e9f861773cbce5f2c302f5684d3282dcec3b7d4766475a3a5248.png","timeStamp":1639756086065},{"screenshot":"670b7feb7d64130114b37a628ecbce17f1f7daadf567a362801de440ec100872.png","timeStamp":1639756087574}],"result":"SUCCESS","precondition":false,"level":3},{"number":8,"description":"Sebastian clicks on ","duration":907,"startTime":"2021-12-17T10:48:07.578-05:00[America/Bogota]","screenshots":[{"screenshot":"670b7feb7d64130114b37a628ecbce17f1f7daadf567a362801de440ec100872.png","timeStamp":1639756087592},{"screenshot":"56fb383c5816ce41e7fa1215a45e406e988abfc08720c160df9c486887598e71.png","timeStamp":1639756088485}],"result":"SUCCESS","precondition":false,"level":3},{"number":9,"description":"Sebastian clicks on ","duration":566,"startTime":"2021-12-17T10:48:08.489-05:00[America/Bogota]","screenshots":[{"screenshot":"56fb383c5816ce41e7fa1215a45e406e988abfc08720c160df9c486887598e71.png","timeStamp":1639756088501},{"screenshot":"5056c880e6eb956c35e14386d12ff8ff50c24fa31145c4d01432c6ee47335c0c.png","timeStamp":1639756089055}],"result":"SUCCESS","precondition":false,"level":3},{"number":10,"description":"Sebastian clicks on ","duration":804,"startTime":"2021-12-17T10:48:09.056-05:00[America/Bogota]","screenshots":[{"screenshot":"5056c880e6eb956c35e14386d12ff8ff50c24fa31145c4d01432c6ee47335c0c.png","timeStamp":1639756089067},{"screenshot":"c457fd4917b88898bd8c3ae5bfd1d37a3420bdd784e3c5773b263f454d77a07d.png","timeStamp":1639756089860}],"result":"SUCCESS","precondition":false,"level":3}]}]},{"number":11,"description":"When cambie los datos de Juan Guillermos hoyos en Mis datos personales","duration":2856,"startTime":"2021-12-17T10:48:09.881-05:00[America/Bogota]","screenshots":[{"screenshot":"c457fd4917b88898bd8c3ae5bfd1d37a3420bdd784e3c5773b263f454d77a07d.png","timeStamp":1639756089889},{"screenshot":"bdc770e965f487c80cdbd8e9e6caf0dcc92db419b3cfd171211dfc2ea336ab50.png","timeStamp":1639756092737}],"result":"SUCCESS","precondition":false,"level":1,"children":[{"number":12,"description":"Sebastian cambiar datos personales","duration":2833,"startTime":"2021-12-17T10:48:09.896-05:00[America/Bogota]","screenshots":[{"screenshot":"c457fd4917b88898bd8c3ae5bfd1d37a3420bdd784e3c5773b263f454d77a07d.png","timeStamp":1639756089905},{"screenshot":"bdc770e965f487c80cdbd8e9e6caf0dcc92db419b3cfd171211dfc2ea336ab50.png","timeStamp":1639756092729}],"result":"SUCCESS","precondition":false,"level":2,"children":[{"number":13,"description":"Sebastian clicks on ","duration":842,"startTime":"2021-12-17T10:48:09.911-05:00[America/Bogota]","screenshots":[{"screenshot":"5d1a67f962c073681701baef89e5d5eaec5094fb4dc587e4790eb2444efd8d20.png","timeStamp":1639756090102},{"screenshot":"c457fd4917b88898bd8c3ae5bfd1d37a3420bdd784e3c5773b263f454d77a07d.png","timeStamp":1639756090753}],"result":"SUCCESS","precondition":false,"level":3},{"number":14,"description":"Sebastian enters \u0027Juan Guillermos\u0027 into ","duration":487,"startTime":"2021-12-17T10:48:10.757-05:00[America/Bogota]","screenshots":[{"screenshot":"c457fd4917b88898bd8c3ae5bfd1d37a3420bdd784e3c5773b263f454d77a07d.png","timeStamp":1639756090765},{"screenshot":"f4b98388ed6fa63ae52112cfdb4835e05c7b2675a7ab576f8b08e8cebb2eab62.png","timeStamp":1639756091244}],"result":"SUCCESS","precondition":false,"level":3},{"number":15,"description":"Sebastian enters \u0027hoyos\u0027 into ","duration":484,"startTime":"2021-12-17T10:48:11.245-05:00[America/Bogota]","screenshots":[{"screenshot":"f4b98388ed6fa63ae52112cfdb4835e05c7b2675a7ab576f8b08e8cebb2eab62.png","timeStamp":1639756091258},{"screenshot":"fe3755df47fe665a99109d1e7b4f0bdcebcad384d8e2c3410903fa87076ea609.png","timeStamp":1639756091729}],"result":"SUCCESS","precondition":false,"level":3},{"number":16,"description":"Sebastian clicks on ","duration":988,"startTime":"2021-12-17T10:48:11.731-05:00[America/Bogota]","screenshots":[{"screenshot":"fe3755df47fe665a99109d1e7b4f0bdcebcad384d8e2c3410903fa87076ea609.png","timeStamp":1639756091741},{"screenshot":"bdc770e965f487c80cdbd8e9e6caf0dcc92db419b3cfd171211dfc2ea336ab50.png","timeStamp":1639756092719}],"result":"SUCCESS","precondition":false,"level":3}]}]},{"number":17,"description":"Then podre ver el mensaje que los cambios se han guardado","duration":298,"startTime":"2021-12-17T10:48:12.738-05:00[America/Bogota]","screenshots":[{"screenshot":"bdc770e965f487c80cdbd8e9e6caf0dcc92db419b3cfd171211dfc2ea336ab50.png","timeStamp":1639756092746},{"screenshot":"54f86560acbcd8e4522e8500a9fb2906c10317f7c5cf3789453a7c2d43f1a752.png","timeStamp":1639756093036}],"result":"SUCCESS","precondition":false,"level":1,"children":[{"number":18,"description":"Then ","duration":200,"startTime":"2021-12-17T10:48:12.826-05:00[America/Bogota]","screenshots":[{"screenshot":"54f86560acbcd8e4522e8500a9fb2906c10317f7c5cf3789453a7c2d43f1a752.png","timeStamp":1639756093016},{"screenshot":"54f86560acbcd8e4522e8500a9fb2906c10317f7c5cf3789453a7c2d43f1a752.png","timeStamp":1639756093026}],"result":"SUCCESS","precondition":false,"level":2}]}]}],"userStory":{"id":"hu-01-configuracion-de-cuenta","storyName":"HU-01 Configuracion de cuenta","path":"src/test/resources/features/LinioConfiguracionDeCuenta.feature","narrative":"  Yo como usuario de Linio\n  Quiero modificar informacion de mi cuenta\n  Para mantenerla actualizada","type":"feature"},"featureTag":{"name":"Features/HU-01 Configuracion de cuenta","type":"feature","displayName":"Features/HU-01 Configuracion de cuenta"},"title":"Actualizar mis datos personales","backgroundTitle":"Logearse en Linio","backgroundDescription":"","tags":[{"name":"Scenario1","type":"tag","displayName":"Scenario1"},{"name":"HU-01 Configuracion de cuenta","type":"feature","displayName":"HU-01 Configuracion de cuenta"}],"startTime":"2021-12-17T10:48:01.675-05:00[America/Bogota]","duration":12029,"projectKey":"","driver":"chrome","isManualTestingUpToDate":false,"dataTable":{"headers":["nombre","apellidos"],"rows":[{"values":["Juan","Guillermos hoyos"],"result":"SUCCESS"}],"predefinedRows":true,"scenarioOutline":"When cambie los datos de \u003cnombre\u003e \u003capellidos\u003e en Mis datos personales\n\rThen podre ver el mensaje que los cambios se han guardado\n\r","dataSetDescriptors":[{"startRow":0,"rowCount":0,"name":""}]},"manual":false,"testSource":"Cucumber","actors":[{"name":"Sebastian","can":["browse the web"]}],"result":"SUCCESS","scenarioOutline":"When cambie los datos de \u003cnombre\u003e \u003capellidos\u003e en Mis datos personales\r\nThen podre ver el mensaje que los cambios se han guardado"}